colour_clf_io/__init__.py
colour_clf_io/elements.py
colour_clf_io/errors.py
colour_clf_io/parsing.py
colour_clf_io/process_list.py
colour_clf_io/process_nodes.py
colour_clf_io/processing.py
colour_clf_io/py.typed
colour_clf_io/values.py
colour_clf_io/tests/__init__.py
colour_clf_io/tests/conftest.py
colour_clf_io/tests/test_clf_SMPTE_ST_2136-1_generation.py
colour_clf_io/tests/test_clf_common.py
colour_clf_io/tests/test_clf_parsing.py
colour_clf_io/tests/test_clf_smpte_st_2136_1_generation.py
colour_clf_io/tests/test_clf_writing.py
colour_clf_io/tests/processing/__init__.py
colour_clf_io/tests/processing/test_asc_cdl.py
colour_clf_io/tests/processing/test_common.py
colour_clf_io/tests/processing/test_exponent.py
colour_clf_io/tests/processing/test_helper.py
colour_clf_io/tests/processing/test_log.py
colour_clf_io/tests/processing/test_lut1d.py
colour_clf_io/tests/processing/test_lut3d.py
colour_clf_io/tests/processing/test_matrix.py
colour_clf_io/tests/processing/test_range.py
colour_clf_io/tests/processing/resources/LMT Kodak 2383 Print Emulation.xml
colour_clf_io/tests/processing/resources/lut1_with_half_domain_sample.xml
colour_clf_io/tests/resources/ACES2065_1_to_ACEScct.xml
colour_clf_io/tests/resources/LMT Kodak 2383 Print Emulation.xml
colour_clf_io/tests/resources/LMT_ARRI_K1S1_709_EI800_v3.xml
colour_clf_io/tests/resources/lut1_with_half_domain_sample.xml
colour_clf_io-0.2.0.dist-info/METADATA
colour_clf_io-0.2.0.dist-info/WHEEL
colour_clf_io-0.2.0.dist-info/licenses/LICENSE
colour_clf_io-0.2.0.dist-info/RECORD
